falken_trace/__init__.py
falken_trace/common/__init__.py
falken_trace/common/cache.py
falken_trace/common/config.py
falken_trace/common/utils.py
falken_trace/py.typed
falken_trace/tracing/__init__.py
falken_trace/tracing/datadog.py
falken_trace/web/__init__.py
falken_trace/web/fastapi.py
falken_trace-0.3.0.dist-info/licenses/LICENSE
falken_trace-0.3.0.dist-info/WHEEL
falken_trace-0.3.0.dist-info/METADATA
falken_trace-0.3.0.dist-info/RECORD
