Metadata-Version: 2.4
Name: falken-trace
Version: 0.3.0
Summary: Enhances traces with code metadata
Keywords: observability,tracing
Author: Baz
Author-email: Baz <info@baz.co>
License-Expression: Apache-2.0
License-File: LICENSE
Classifier: Programming Language :: Python :: 3 :: Only
Classifier: Programming Language :: Python :: 3.10
Classifier: Programming Language :: Python :: 3.11
Classifier: Programming Language :: Python :: 3.12
Classifier: Programming Language :: Python :: 3.13
Classifier: Programming Language :: Python :: 3.14
Classifier: Typing :: Typed
Requires-Dist: typing-extensions>=4.6.0,<5.0.0
Requires-Dist: wrapt>=1.15.0,<3.0.0
Requires-Python: >=3.10
Project-URL: Changelog, https://github.com/baz-scm/falken-trace-py/blob/main/CHANGELOG.md
Project-URL: Homepage, https://github.com/baz-scm/falken-trace-py
Project-URL: Releases, https://github.com/baz-scm/falken-trace-py/releases
Project-URL: Repository, https://github.com/baz-scm/falken-trace-py
